<annotation>
	<folder></folder>
	<filename>Hardhat0231_jpg.rf.21e0385a83268dbf6dfa54e931b92519.jpg</filename>
	<path>Hardhat0231_jpg.rf.21e0385a83268dbf6dfa54e931b92519.jpg</path>
	<source>
		<database>roboflow.com</database>
	</source>
	<size>
		<width>900</width>
		<height>900</height>
		<depth>3</depth>
	</size>
	<segmented>0</segmented>
	<object>
		<name>NoHelmet</name>
		<pose>Unspecified</pose>
		<truncated>0</truncated>
		<difficult>0</difficult>
		<occluded>0</occluded>
		<bndbox>
			<xmin>231</xmin>
			<xmax>347</xmax>
			<ymin>217</ymin>
			<ymax>373</ymax>
		</bndbox>
	</object>
	<object>
		<name>NoHelmet</name>
		<pose>Unspecified</pose>
		<truncated>0</truncated>
		<difficult>0</difficult>
		<occluded>0</occluded>
		<bndbox>
			<xmin>399</xmin>
			<xmax>455</xmax>
			<ymin>282</ymin>
			<ymax>353</ymax>
		</bndbox>
	</object>
	<object>
		<name>NoHelmet</name>
		<pose>Unspecified</pose>
		<truncated>0</truncated>
		<difficult>0</difficult>
		<occluded>0</occluded>
		<bndbox>
			<xmin>568</xmin>
			<xmax>622</xmax>
			<ymin>276</ymin>
			<ymax>346</ymax>
		</bndbox>
	</object>
	<object>
		<name>NoHelmet</name>
		<pose>Unspecified</pose>
		<truncated>0</truncated>
		<difficult>0</difficult>
		<occluded>0</occluded>
		<bndbox>
			<xmin>745</xmin>
			<xmax>815</xmax>
			<ymin>345</ymin>
			<ymax>424</ymax>
		</bndbox>
	</object>
</annotation>
