<annotation>
	<folder></folder>
	<filename>Hardhat0187_jpg.rf.4765116c8b4ab3a8c277802c8d3ba99b.jpg</filename>
	<path>Hardhat0187_jpg.rf.4765116c8b4ab3a8c277802c8d3ba99b.jpg</path>
	<source>
		<database>roboflow.com</database>
	</source>
	<size>
		<width>640</width>
		<height>640</height>
		<depth>3</depth>
	</size>
	<segmented>0</segmented>
	<object>
		<name>NoHelmet</name>
		<pose>Unspecified</pose>
		<truncated>0</truncated>
		<difficult>0</difficult>
		<occluded>0</occluded>
		<bndbox>
			<xmin>219</xmin>
			<xmax>290</xmax>
			<ymin>145</ymin>
			<ymax>201</ymax>
		</bndbox>
	</object>
	<object>
		<name>NoHelmet</name>
		<pose>Unspecified</pose>
		<truncated>0</truncated>
		<difficult>0</difficult>
		<occluded>0</occluded>
		<bndbox>
			<xmin>217</xmin>
			<xmax>323</xmax>
			<ymin>412</ymin>
			<ymax>502</ymax>
		</bndbox>
	</object>
</annotation>
