<annotation>
	<folder></folder>
	<filename>HardHat0620_jpg.rf.b53a07128efe8d2d063ade05d027d6af.jpg</filename>
	<path>HardHat0620_jpg.rf.b53a07128efe8d2d063ade05d027d6af.jpg</path>
	<source>
		<database>roboflow.com</database>
	</source>
	<size>
		<width>640</width>
		<height>640</height>
		<depth>3</depth>
	</size>
	<segmented>0</segmented>
	<object>
		<name>Helmet</name>
		<pose>Unspecified</pose>
		<truncated>0</truncated>
		<difficult>0</difficult>
		<occluded>0</occluded>
		<bndbox>
			<xmin>241</xmin>
			<xmax>354</xmax>
			<ymin>86</ymin>
			<ymax>211</ymax>
		</bndbox>
	</object>
	<object>
		<name>Helmet</name>
		<pose>Unspecified</pose>
		<truncated>0</truncated>
		<difficult>0</difficult>
		<occluded>0</occluded>
		<bndbox>
			<xmin>213</xmin>
			<xmax>415</xmax>
			<ymin>227</ymin>
			<ymax>523</ymax>
		</bndbox>
	</object>
</annotation>
