<annotation>
	<folder></folder>
	<filename>HardHat0539_jpg.rf.ee76d7853ec973609419ccecf6497bcd.jpg</filename>
	<path>HardHat0539_jpg.rf.ee76d7853ec973609419ccecf6497bcd.jpg</path>
	<source>
		<database>roboflow.com</database>
	</source>
	<size>
		<width>640</width>
		<height>640</height>
		<depth>3</depth>
	</size>
	<segmented>0</segmented>
	<object>
		<name>Helmet</name>
		<pose>Unspecified</pose>
		<truncated>0</truncated>
		<difficult>0</difficult>
		<occluded>0</occluded>
		<bndbox>
			<xmin>487</xmin>
			<xmax>498</xmax>
			<ymin>426</ymin>
			<ymax>440</ymax>
		</bndbox>
	</object>
	<object>
		<name>Helmet</name>
		<pose>Unspecified</pose>
		<truncated>0</truncated>
		<difficult>0</difficult>
		<occluded>0</occluded>
		<bndbox>
			<xmin>265</xmin>
			<xmax>303</xmax>
			<ymin>266</ymin>
			<ymax>308</ymax>
		</bndbox>
	</object>
	<object>
		<name>Helmet</name>
		<pose>Unspecified</pose>
		<truncated>0</truncated>
		<difficult>0</difficult>
		<occluded>0</occluded>
		<bndbox>
			<xmin>97</xmin>
			<xmax>165</xmax>
			<ymin>106</ymin>
			<ymax>178</ymax>
		</bndbox>
	</object>
	<object>
		<name>Helmet</name>
		<pose>Unspecified</pose>
		<truncated>0</truncated>
		<difficult>0</difficult>
		<occluded>0</occluded>
		<bndbox>
			<xmin>312</xmin>
			<xmax>340</xmax>
			<ymin>405</ymin>
			<ymax>434</ymax>
		</bndbox>
	</object>
	<object>
		<name>Jacket</name>
		<pose>Unspecified</pose>
		<truncated>0</truncated>
		<difficult>0</difficult>
		<occluded>0</occluded>
		<bndbox>
			<xmin>38</xmin>
			<xmax>158</xmax>
			<ymin>177</ymin>
			<ymax>424</ymax>
		</bndbox>
	</object>
	<object>
		<name>Jacket</name>
		<pose>Unspecified</pose>
		<truncated>0</truncated>
		<difficult>0</difficult>
		<occluded>0</occluded>
		<bndbox>
			<xmin>230</xmin>
			<xmax>298</xmax>
			<ymin>310</ymin>
			<ymax>451</ymax>
		</bndbox>
	</object>
	<object>
		<name>Jacket</name>
		<pose>Unspecified</pose>
		<truncated>0</truncated>
		<difficult>0</difficult>
		<occluded>0</occluded>
		<bndbox>
			<xmin>295</xmin>
			<xmax>371</xmax>
			<ymin>440</ymin>
			<ymax>559</ymax>
		</bndbox>
	</object>
	<object>
		<name>Jacket</name>
		<pose>Unspecified</pose>
		<truncated>0</truncated>
		<difficult>0</difficult>
		<occluded>0</occluded>
		<bndbox>
			<xmin>467</xmin>
			<xmax>488</xmax>
			<ymin>427</ymin>
			<ymax>448</ymax>
		</bndbox>
	</object>
</annotation>
