<annotation>
	<folder></folder>
	<filename>HardHat0532_jpg.rf.588e29a19a63014a36b543a9e21d91c0.jpg</filename>
	<path>HardHat0532_jpg.rf.588e29a19a63014a36b543a9e21d91c0.jpg</path>
	<source>
		<database>roboflow.com</database>
	</source>
	<size>
		<width>640</width>
		<height>640</height>
		<depth>3</depth>
	</size>
	<segmented>0</segmented>
	<object>
		<name>NoHelmet</name>
		<pose>Unspecified</pose>
		<truncated>0</truncated>
		<difficult>0</difficult>
		<occluded>0</occluded>
		<bndbox>
			<xmin>265</xmin>
			<xmax>285</xmax>
			<ymin>222</ymin>
			<ymax>237</ymax>
		</bndbox>
	</object>
	<object>
		<name>NoHelmet</name>
		<pose>Unspecified</pose>
		<truncated>0</truncated>
		<difficult>0</difficult>
		<occluded>0</occluded>
		<bndbox>
			<xmin>371</xmin>
			<xmax>392</xmax>
			<ymin>224</ymin>
			<ymax>242</ymax>
		</bndbox>
	</object>
	<object>
		<name>NoHelmet</name>
		<pose>Unspecified</pose>
		<truncated>0</truncated>
		<difficult>0</difficult>
		<occluded>0</occluded>
		<bndbox>
			<xmin>332</xmin>
			<xmax>364</xmax>
			<ymin>414</ymin>
			<ymax>439</ymax>
		</bndbox>
	</object>
	<object>
		<name>NoJacket</name>
		<pose>Unspecified</pose>
		<truncated>0</truncated>
		<difficult>0</difficult>
		<occluded>0</occluded>
		<bndbox>
			<xmin>274</xmin>
			<xmax>340</xmax>
			<ymin>432</ymin>
			<ymax>493</ymax>
		</bndbox>
	</object>
	<object>
		<name>NoJacket</name>
		<pose>Unspecified</pose>
		<truncated>0</truncated>
		<difficult>0</difficult>
		<occluded>0</occluded>
		<bndbox>
			<xmin>253</xmin>
			<xmax>282</xmax>
			<ymin>236</ymin>
			<ymax>274</ymax>
		</bndbox>
	</object>
	<object>
		<name>NoJacket</name>
		<pose>Unspecified</pose>
		<truncated>0</truncated>
		<difficult>0</difficult>
		<occluded>0</occluded>
		<bndbox>
			<xmin>374</xmin>
			<xmax>401</xmax>
			<ymin>237</ymin>
			<ymax>277</ymax>
		</bndbox>
	</object>
</annotation>
