<annotation>
	<folder></folder>
	<filename>HardHat0365_jpg.rf.d458597243d3121fd1e757d5376e653a.jpg</filename>
	<path>HardHat0365_jpg.rf.d458597243d3121fd1e757d5376e653a.jpg</path>
	<source>
		<database>roboflow.com</database>
	</source>
	<size>
		<width>640</width>
		<height>640</height>
		<depth>3</depth>
	</size>
	<segmented>0</segmented>
	<object>
		<name>NoHelmet</name>
		<pose>Unspecified</pose>
		<truncated>0</truncated>
		<difficult>0</difficult>
		<occluded>0</occluded>
		<bndbox>
			<xmin>533</xmin>
			<xmax>575</xmax>
			<ymin>117</ymin>
			<ymax>200</ymax>
		</bndbox>
	</object>
	<object>
		<name>NoHelmet</name>
		<pose>Unspecified</pose>
		<truncated>0</truncated>
		<difficult>0</difficult>
		<occluded>0</occluded>
		<bndbox>
			<xmin>477</xmin>
			<xmax>528</xmax>
			<ymin>138</ymin>
			<ymax>226</ymax>
		</bndbox>
	</object>
	<object>
		<name>NoHelmet</name>
		<pose>Unspecified</pose>
		<truncated>0</truncated>
		<difficult>0</difficult>
		<occluded>0</occluded>
		<bndbox>
			<xmin>366</xmin>
			<xmax>404</xmax>
			<ymin>212</ymin>
			<ymax>270</ymax>
		</bndbox>
	</object>
	<object>
		<name>NoHelmet</name>
		<pose>Unspecified</pose>
		<truncated>0</truncated>
		<difficult>0</difficult>
		<occluded>0</occluded>
		<bndbox>
			<xmin>277</xmin>
			<xmax>313</xmax>
			<ymin>121</ymin>
			<ymax>194</ymax>
		</bndbox>
	</object>
	<object>
		<name>NoHelmet</name>
		<pose>Unspecified</pose>
		<truncated>0</truncated>
		<difficult>0</difficult>
		<occluded>0</occluded>
		<bndbox>
			<xmin>301</xmin>
			<xmax>336</xmax>
			<ymin>299</ymin>
			<ymax>370</ymax>
		</bndbox>
	</object>
	<object>
		<name>Jacket</name>
		<pose>Unspecified</pose>
		<truncated>0</truncated>
		<difficult>0</difficult>
		<occluded>0</occluded>
		<bndbox>
			<xmin>339</xmin>
			<xmax>402</xmax>
			<ymin>242</ymin>
			<ymax>359</ymax>
		</bndbox>
	</object>
	<object>
		<name>Jacket</name>
		<pose>Unspecified</pose>
		<truncated>0</truncated>
		<difficult>0</difficult>
		<occluded>0</occluded>
		<bndbox>
			<xmin>255</xmin>
			<xmax>331</xmax>
			<ymin>170</ymin>
			<ymax>293</ymax>
		</bndbox>
	</object>
	<object>
		<name>Jacket</name>
		<pose>Unspecified</pose>
		<truncated>0</truncated>
		<difficult>0</difficult>
		<occluded>0</occluded>
		<bndbox>
			<xmin>211</xmin>
			<xmax>316</xmax>
			<ymin>267</ymin>
			<ymax>359</ymax>
		</bndbox>
	</object>
	<object>
		<name>Jacket</name>
		<pose>Unspecified</pose>
		<truncated>0</truncated>
		<difficult>0</difficult>
		<occluded>0</occluded>
		<bndbox>
			<xmin>460</xmin>
			<xmax>533</xmax>
			<ymin>207</ymin>
			<ymax>411</ymax>
		</bndbox>
	</object>
	<object>
		<name>Jacket</name>
		<pose>Unspecified</pose>
		<truncated>0</truncated>
		<difficult>0</difficult>
		<occluded>0</occluded>
		<bndbox>
			<xmin>522</xmin>
			<xmax>585</xmax>
			<ymin>191</ymin>
			<ymax>351</ymax>
		</bndbox>
	</object>
</annotation>
