<annotation>
	<folder></folder>
	<filename>HardHat0377_jpg.rf.a9fa4870219998c293db307e77b4b54d.jpg</filename>
	<path>HardHat0377_jpg.rf.a9fa4870219998c293db307e77b4b54d.jpg</path>
	<source>
		<database>roboflow.com</database>
	</source>
	<size>
		<width>640</width>
		<height>640</height>
		<depth>3</depth>
	</size>
	<segmented>0</segmented>
	<object>
		<name>Helmet</name>
		<pose>Unspecified</pose>
		<truncated>0</truncated>
		<difficult>0</difficult>
		<occluded>0</occluded>
		<bndbox>
			<xmin>17</xmin>
			<xmax>47</xmax>
			<ymin>211</ymin>
			<ymax>245</ymax>
		</bndbox>
	</object>
	<object>
		<name>Helmet</name>
		<pose>Unspecified</pose>
		<truncated>0</truncated>
		<difficult>0</difficult>
		<occluded>0</occluded>
		<bndbox>
			<xmin>50</xmin>
			<xmax>76</xmax>
			<ymin>206</ymin>
			<ymax>242</ymax>
		</bndbox>
	</object>
	<object>
		<name>Helmet</name>
		<pose>Unspecified</pose>
		<truncated>0</truncated>
		<difficult>0</difficult>
		<occluded>0</occluded>
		<bndbox>
			<xmin>101</xmin>
			<xmax>130</xmax>
			<ymin>213</ymin>
			<ymax>243</ymax>
		</bndbox>
	</object>
	<object>
		<name>Helmet</name>
		<pose>Unspecified</pose>
		<truncated>0</truncated>
		<difficult>0</difficult>
		<occluded>0</occluded>
		<bndbox>
			<xmin>139</xmin>
			<xmax>168</xmax>
			<ymin>212</ymin>
			<ymax>243</ymax>
		</bndbox>
	</object>
	<object>
		<name>Helmet</name>
		<pose>Unspecified</pose>
		<truncated>0</truncated>
		<difficult>0</difficult>
		<occluded>0</occluded>
		<bndbox>
			<xmin>174</xmin>
			<xmax>210</xmax>
			<ymin>181</ymin>
			<ymax>224</ymax>
		</bndbox>
	</object>
	<object>
		<name>Helmet</name>
		<pose>Unspecified</pose>
		<truncated>0</truncated>
		<difficult>0</difficult>
		<occluded>0</occluded>
		<bndbox>
			<xmin>205</xmin>
			<xmax>233</xmax>
			<ymin>207</ymin>
			<ymax>241</ymax>
		</bndbox>
	</object>
	<object>
		<name>Helmet</name>
		<pose>Unspecified</pose>
		<truncated>0</truncated>
		<difficult>0</difficult>
		<occluded>0</occluded>
		<bndbox>
			<xmin>306</xmin>
			<xmax>343</xmax>
			<ymin>194</ymin>
			<ymax>248</ymax>
		</bndbox>
	</object>
	<object>
		<name>Helmet</name>
		<pose>Unspecified</pose>
		<truncated>0</truncated>
		<difficult>0</difficult>
		<occluded>0</occluded>
		<bndbox>
			<xmin>361</xmin>
			<xmax>396</xmax>
			<ymin>294</ymin>
			<ymax>348</ymax>
		</bndbox>
	</object>
	<object>
		<name>Helmet</name>
		<pose>Unspecified</pose>
		<truncated>0</truncated>
		<difficult>0</difficult>
		<occluded>0</occluded>
		<bndbox>
			<xmin>454</xmin>
			<xmax>486</xmax>
			<ymin>308</ymin>
			<ymax>362</ymax>
		</bndbox>
	</object>
	<object>
		<name>Helmet</name>
		<pose>Unspecified</pose>
		<truncated>0</truncated>
		<difficult>0</difficult>
		<occluded>0</occluded>
		<bndbox>
			<xmin>477</xmin>
			<xmax>512</xmax>
			<ymin>302</ymin>
			<ymax>352</ymax>
		</bndbox>
	</object>
	<object>
		<name>Helmet</name>
		<pose>Unspecified</pose>
		<truncated>0</truncated>
		<difficult>0</difficult>
		<occluded>0</occluded>
		<bndbox>
			<xmin>554</xmin>
			<xmax>576</xmax>
			<ymin>168</ymin>
			<ymax>190</ymax>
		</bndbox>
	</object>
	<object>
		<name>Helmet</name>
		<pose>Unspecified</pose>
		<truncated>0</truncated>
		<difficult>0</difficult>
		<occluded>0</occluded>
		<bndbox>
			<xmin>581</xmin>
			<xmax>611</xmax>
			<ymin>139</ymin>
			<ymax>167</ymax>
		</bndbox>
	</object>
	<object>
		<name>Jacket</name>
		<pose>Unspecified</pose>
		<truncated>0</truncated>
		<difficult>0</difficult>
		<occluded>0</occluded>
		<bndbox>
			<xmin>15</xmin>
			<xmax>57</xmax>
			<ymin>251</ymin>
			<ymax>357</ymax>
		</bndbox>
	</object>
	<object>
		<name>Jacket</name>
		<pose>Unspecified</pose>
		<truncated>0</truncated>
		<difficult>0</difficult>
		<occluded>0</occluded>
		<bndbox>
			<xmin>53</xmin>
			<xmax>104</xmax>
			<ymin>266</ymin>
			<ymax>346</ymax>
		</bndbox>
	</object>
	<object>
		<name>Jacket</name>
		<pose>Unspecified</pose>
		<truncated>0</truncated>
		<difficult>0</difficult>
		<occluded>0</occluded>
		<bndbox>
			<xmin>102</xmin>
			<xmax>145</xmax>
			<ymin>256</ymin>
			<ymax>356</ymax>
		</bndbox>
	</object>
	<object>
		<name>Jacket</name>
		<pose>Unspecified</pose>
		<truncated>0</truncated>
		<difficult>0</difficult>
		<occluded>0</occluded>
		<bndbox>
			<xmin>169</xmin>
			<xmax>217</xmax>
			<ymin>236</ymin>
			<ymax>352</ymax>
		</bndbox>
	</object>
	<object>
		<name>Jacket</name>
		<pose>Unspecified</pose>
		<truncated>0</truncated>
		<difficult>0</difficult>
		<occluded>0</occluded>
		<bndbox>
			<xmin>217</xmin>
			<xmax>250</xmax>
			<ymin>247</ymin>
			<ymax>323</ymax>
		</bndbox>
	</object>
	<object>
		<name>Jacket</name>
		<pose>Unspecified</pose>
		<truncated>0</truncated>
		<difficult>0</difficult>
		<occluded>0</occluded>
		<bndbox>
			<xmin>277</xmin>
			<xmax>340</xmax>
			<ymin>239</ymin>
			<ymax>342</ymax>
		</bndbox>
	</object>
	<object>
		<name>Jacket</name>
		<pose>Unspecified</pose>
		<truncated>0</truncated>
		<difficult>0</difficult>
		<occluded>0</occluded>
		<bndbox>
			<xmin>395</xmin>
			<xmax>443</xmax>
			<ymin>296</ymin>
			<ymax>346</ymax>
		</bndbox>
	</object>
	<object>
		<name>Jacket</name>
		<pose>Unspecified</pose>
		<truncated>0</truncated>
		<difficult>0</difficult>
		<occluded>0</occluded>
		<bndbox>
			<xmin>569</xmin>
			<xmax>640</xmax>
			<ymin>179</ymin>
			<ymax>304</ymax>
		</bndbox>
	</object>
	<object>
		<name>Jacket</name>
		<pose>Unspecified</pose>
		<truncated>0</truncated>
		<difficult>0</difficult>
		<occluded>0</occluded>
		<bndbox>
			<xmin>542</xmin>
			<xmax>577</xmax>
			<ymin>204</ymin>
			<ymax>286</ymax>
		</bndbox>
	</object>
	<object>
		<name>Jacket</name>
		<pose>Unspecified</pose>
		<truncated>0</truncated>
		<difficult>0</difficult>
		<occluded>0</occluded>
		<bndbox>
			<xmin>501</xmin>
			<xmax>564</xmax>
			<ymin>338</ymin>
			<ymax>417</ymax>
		</bndbox>
	</object>
	<object>
		<name>NoJacket</name>
		<pose>Unspecified</pose>
		<truncated>0</truncated>
		<difficult>0</difficult>
		<occluded>0</occluded>
		<bndbox>
			<xmin>139</xmin>
			<xmax>176</xmax>
			<ymin>246</ymin>
			<ymax>351</ymax>
		</bndbox>
	</object>
</annotation>
