<annotation>
	<folder></folder>
	<filename>Hardhat0107_jpg.rf.9bb292ac702cbf47f1d3fb0d17b26bcc.jpg</filename>
	<path>Hardhat0107_jpg.rf.9bb292ac702cbf47f1d3fb0d17b26bcc.jpg</path>
	<source>
		<database>roboflow.com</database>
	</source>
	<size>
		<width>900</width>
		<height>900</height>
		<depth>3</depth>
	</size>
	<segmented>0</segmented>
	<object>
		<name>NoHelmet</name>
		<pose>Unspecified</pose>
		<truncated>0</truncated>
		<difficult>0</difficult>
		<occluded>0</occluded>
		<bndbox>
			<xmin>156</xmin>
			<xmax>246</xmax>
			<ymin>1</ymin>
			<ymax>24</ymax>
		</bndbox>
	</object>
	<object>
		<name>NoHelmet</name>
		<pose>Unspecified</pose>
		<truncated>0</truncated>
		<difficult>0</difficult>
		<occluded>0</occluded>
		<bndbox>
			<xmin>570</xmin>
			<xmax>618</xmax>
			<ymin>5</ymin>
			<ymax>42</ymax>
		</bndbox>
	</object>
	<object>
		<name>NoHelmet</name>
		<pose>Unspecified</pose>
		<truncated>0</truncated>
		<difficult>0</difficult>
		<occluded>0</occluded>
		<bndbox>
			<xmin>694</xmin>
			<xmax>765</xmax>
			<ymin>10</ymin>
			<ymax>54</ymax>
		</bndbox>
	</object>
	<object>
		<name>Helmet</name>
		<pose>Unspecified</pose>
		<truncated>0</truncated>
		<difficult>0</difficult>
		<occluded>0</occluded>
		<bndbox>
			<xmin>382</xmin>
			<xmax>465</xmax>
			<ymin>1</ymin>
			<ymax>46</ymax>
		</bndbox>
	</object>
</annotation>
