<annotation>
	<folder></folder>
	<filename>Hardhat0017_JPG.rf.c4f54277f25147a0223e7e8c161e85c8.jpg</filename>
	<path>Hardhat0017_JPG.rf.c4f54277f25147a0223e7e8c161e85c8.jpg</path>
	<source>
		<database>roboflow.com</database>
	</source>
	<size>
		<width>640</width>
		<height>640</height>
		<depth>3</depth>
	</size>
	<segmented>0</segmented>
	<object>
		<name>NoHelmet</name>
		<pose>Unspecified</pose>
		<truncated>0</truncated>
		<difficult>0</difficult>
		<occluded>0</occluded>
		<bndbox>
			<xmin>230</xmin>
			<xmax>250</xmax>
			<ymin>107</ymin>
			<ymax>130</ymax>
		</bndbox>
	</object>
	<object>
		<name>NoHelmet</name>
		<pose>Unspecified</pose>
		<truncated>0</truncated>
		<difficult>0</difficult>
		<occluded>0</occluded>
		<bndbox>
			<xmin>176</xmin>
			<xmax>195</xmax>
			<ymin>160</ymin>
			<ymax>186</ymax>
		</bndbox>
	</object>
</annotation>
